myslideslive/__init__.py
myslideslive/_nbdev.py
myslideslive/cli.py
myslideslive/slideslive.py
myslideslive/test_helper.py
myslideslive-0.7.dist-info/LICENSE
myslideslive-0.7.dist-info/METADATA
myslideslive-0.7.dist-info/WHEEL
myslideslive-0.7.dist-info/entry_points.txt
myslideslive-0.7.dist-info/top_level.txt
myslideslive-0.7.dist-info/RECORD
