Metadata-Version: 2.1
Name: myslideslive
Version: 0.7
Summary: Download the (video) slides of your SlidesLive talk
Home-page: https://github.com/So-Cool/myslideslive/tree/master/
Author: Kacper Sokol
Author-email: dev@kcpr.me
License: BSD License
Keywords: SlidesLive
Platform: UNKNOWN
Classifier: Development Status :: 7 - Inactive
Classifier: Intended Audience :: Developers
Classifier: Natural Language :: English
Classifier: Programming Language :: Python :: 3.6
Classifier: Programming Language :: Python :: 3.7
Classifier: Programming Language :: Python :: 3.8
Classifier: License :: OSI Approved :: BSD License
Requires-Python: >=3.6
Requires-Dist: requests
Requires-Dist: lxml
